Metadata-Version: 1.0
Name: distributions-nanya
Version: 0.1
Summary: Gaussian distribution and Binomial distribution
Home-page: UNKNOWN
Author: Adeniran Rachel
Author-email: ihunanyayekini@gmail.com
License: UNKNOWN
Platform: UNKNOWN
